stockai/__init__.py
stockai/utils.py
stockai/wealthsimple/__init__.py
stockai/wealthsimple/requests.py
stockai/wealthsimple/stock.py
stockai/yahoo/__init__.py
stockai/yahoo/base.py
stockai/yahoo/stock.py
stockai-1.5.0.dist-info/LICENSE
stockai-1.5.0.dist-info/METADATA
stockai-1.5.0.dist-info/WHEEL
stockai-1.5.0.dist-info/top_level.txt
stockai-1.5.0.dist-info/RECORD
