Metadata-Version: 2.1
Name: stockai
Version: 1.5.0
Summary: Get stock info from Yahoo! Finance
Home-page: https://github.com/dalenguyen/stockai
Author: Dale Nguyen
Author-email: dale@dalenguyen.me
License: UNKNOWN
Platform: UNKNOWN
Classifier: Programming Language :: Python :: 3
Classifier: License :: OSI Approved :: GNU General Public License v3 (GPLv3)
Classifier: Operating System :: OS Independent
Requires-Dist: ciso8601
Requires-Dist: requests
Requires-Dist: loguru
